README.md
setup.py
app/__init__.py
open_dev.to.egg-info/PKG-INFO
open_dev.to.egg-info/SOURCES.txt
open_dev.to.egg-info/dependency_links.txt
open_dev.to.egg-info/entry_points.txt
open_dev.to.egg-info/requires.txt
open_dev.to.egg-info/top_level.txt