Metadata-Version: 2.1
Name: open-dev.to
Version: 1.0
Summary: Open a new dev.to browser tab from your terminal
Home-page: https://github.com/wangonya/open-dev.to
Author: Kinyanjui Wangonya
Author-email: kwangonya@gmail.com
License: MIT
Platform: UNKNOWN
Classifier: License :: OSI Approved :: MIT License
Classifier: Programming Language :: Python :: 3
Classifier: Programming Language :: Python :: 3.7
